{
  "users": [
    {
      "aud": "auth0|5ca4bd968bbc2e10cd7accc1",
      "name": "me1",
      "id": 1
    },
    {
      "aud": "auth0|5ca4c1e5158ad41148802fdf",
      "name": "me2",
      "id": 2
    }
  ],
  "dogs": [
    {
      "id": 3,
      "userId": 2,
      "name": "Whip",
      "breed": "Greyhound",
      "age": "2",
      "active": "true",
      "neutered": "false"
    },
    {
      "name": "Skip",
      "breed": "Greyhound",
      "neutered": "false",
      "active": "true",
      "age": "2",
      "userId": 2,
      "id": 4
    },
    {
      "id": 5,
      "userId": 2,
      "name": "SKip",
      "breed": "",
      "age": "3",
      "active": "false",
      "neutered": "false"
    }
  ],
  "exercises": [
    {
      "userId": 2,
      "name": "Flirt Pole",
      "id": 2
    },
    {
      "id": 3,
      "userId": 2,
      "name": "DockDiving"
    },
    {
      "id": 4,
      "userId": 2,
      "name": "Agility Course"
    },
    {
      "userId": 2,
      "name": "Fetch",
      "id": 5
    }
  ],
  "foods": [
    {
      "id": 1,
      "userId": 1,
      "name": "True Chews",
      "brand": "Tyson Pet Products",
      "serving": "one piece",
      "calories": 47
    },
    {
      "userId": 2,
      "name": "Kibble",
      "brand": "Purina One",
      "serving": ".75 Cups",
      "calories": 245,
      "id": 2
    },
    {
      "userId": 2,
      "brand": "Blue Buffalo",
      "name": "Kibble",
      "serving": "1 Cup",
      "calories": 300,
      "id": 3
    },
    {
      "userId": 2,
      "name": "Kibble",
      "brand": "Hills Science Diet",
      "serving": "1 Cup",
      "calories": 275,
      "id": 4
    },
    {
      "userId": 2,
      "brand": "Purina Puppy",
      "name": "Kibble",
      "serving": ".5 Cups",
      "calories": 150,
      "id": 5
    },
    {
      "userId": 2,
      "brand": "s",
      "name": "Chocolate covered peanuts",
      "serving": "",
      "calories": 23,
      "id": 6
    },
    {
      "userId": 2,
      "brand": "s",
      "name": "Chocolate covered peanuts",
      "serving": "",
      "calories": 24,
      "id": 7
    },
    {
      "userId": 2,
      "brand": "",
      "name": "Chocolate covered peanuts",
      "serving": "",
      "calories": null,
      "id": 8
    }
  ],
  "exerciseEntries": [
    {
      "dogId": 3,
      "date": "2019-04-03",
      "id": 2,
      "time": 15,
      "exerciseId": 2
    },
    {
      "dogId": 3,
      "date": "2019-04-04",
      "id": 6,
      "time": 10,
      "exerciseId": 2
    }
  ],
  "foodEntries": [
    {
      "dogId": 3,
      "date": "2019-04-03",
      "foodId": 1,
      "serving": 2,
      "id": 7
    },
    {
      "dogId": 3,
      "date": "2019-04-03",
      "foodId": 2,
      "serving": 2,
      "id": 8
    },
    {
      "dogId": 3,
      "date": "2019-04-03",
      "foodId": 1,
      "serving": 2,
      "id": 9
    },
    {
      "dogId": 3,
      "date": "2019-04-02",
      "foodId": 2,
      "serving": 2,
      "id": 10
    },
    {
      "dogId": 3,
      "date": "2019-04-04",
      "foodId": 1,
      "serving": 3,
      "id": 11
    }
  ],
  "weight": [
    {
      "dogId": "3",
      "weight": "24",
      "date": "2019-04-02",
      "id": 1
    },
    {
      "dogId": "3",
      "weight": "24",
      "date": "2019-04-03",
      "id": 5
    },
    {
      "dogId": "3",
      "weight": "24",
      "date": "2019-04-03",
      "id": 6
    },
    {
      "dogId": "3",
      "weight": "19",
      "date": "2019-04-03",
      "id": 7
    },
    {
      "dogId": "3",
      "weight": "24",
      "date": "2019-04-03",
      "id": 8
    }
  ],
  "behavior": []
}